PiDigit/__init__.py
PiDigit/pi_digit.py
PiDigit/pi_digit_core.py
PiDigit/PiBin/__init__.py
PiDigit/PiBin/pi_digit.so
pidigit-1.0.dist-info/METADATA
pidigit-1.0.dist-info/WHEEL
pidigit-1.0.dist-info/top_level.txt
pidigit-1.0.dist-info/RECORD
