Metadata-Version: 2.1
Name: pidigit
Version: 1.0
Summary: A python wrapper for PiDigit
Home-page: UNKNOWN
Author: Sadaok
Author-email: sadok.rezgui@adagos.com
License: Proprietary
Platform: UNKNOWN
Requires-Python: >=3.8
Requires-Dist: matplotlib (>=3.0)
Requires-Dist: numpy (>=1.22)
Requires-Dist: torch (==2.7.1)
Requires-Dist: torchaudio (==2.7.1)
Requires-Dist: torchvision (==0.22.1)
